setup.py
tradetuya/__init__.py
tradetuya/aescipher.py
tradetuya/helper.py
tradetuya.egg-info/PKG-INFO
tradetuya.egg-info/SOURCES.txt
tradetuya.egg-info/dependency_links.txt
tradetuya.egg-info/requires.txt
tradetuya.egg-info/top_level.txt