Metadata-Version: 2.1
Name: tradetuya
Version: 1.0.2
Summary: Python interface to Tuya WiFi smart devices.
Home-page: https://github.com/TradeFace/tuya/
Author: tradeface
Author-email: 
License: MIT
Keywords: home automation,tuya
Platform: any
Classifier: Development Status :: 4 - Beta
Classifier: Intended Audience :: Developers
Classifier: Topic :: Home Automation
Classifier: License :: OSI Approved :: MIT License
Classifier: Programming Language :: Python
Classifier: Programming Language :: Python :: 2
Classifier: Programming Language :: Python :: 3
Classifier: Programming Language :: Python :: 3.6
Classifier: Topic :: Home Automation
